airflow_providers_couchbase/__about__.py
airflow_providers_couchbase/__init__.py
airflow_providers_couchbase/hooks/__init__.py
airflow_providers_couchbase/hooks/couchbase.py
airflow_providers_couchbase-1.0.0.dist-info/METADATA
airflow_providers_couchbase-1.0.0.dist-info/WHEEL
airflow_providers_couchbase-1.0.0.dist-info/entry_points.txt
airflow_providers_couchbase-1.0.0.dist-info/licenses/LICENSE
airflow_providers_couchbase-1.0.0.dist-info/RECORD
