Metadata-Version: 2.3
Name: airflow-providers-couchbase
Version: 1.0.0
Summary: A package to simplify connecting to the couchbase nosql database from Apache Airflow
Project-URL: Documentation, https://github.com/Couchbase-Ecosystem/airflow-providers-couchbase#readme
Project-URL: Issues, https://github.com/Couchbase-Ecosystem/airflow-providers-couchbase/issues
Project-URL: Source, https://github.com/Couchbase-Ecosystem/airflow-providers-couchbase
Author-email: Shyam Venkat <shyam.venkat@couchbase.com>
License:                                  Apache License
License-File: LICENSE
Classifier: Development Status :: 4 - Beta
Classifier: Programming Language :: Python
Classifier: Programming Language :: Python :: 3.8
Classifier: Programming Language :: Python :: 3.9
Classifier: Programming Language :: Python :: 3.10
Classifier: Programming Language :: Python :: 3.11
Classifier: Programming Language :: Python :: 3.12
Classifier: Programming Language :: Python :: Implementation :: CPython
Classifier: Programming Language :: Python :: Implementation :: PyPy
Requires-Python: >=3.7
Requires-Dist: apache-airflow>=2.2
Requires-Dist: couchbase==4.*
